PyDeepLib/__init__.py
PyDeepLib/layers.py
PyDeepLib/loggingin.py
PyDeepLib/speedfilein.py
PyDeepLib/tensorclass.py
Tensor_Library-0.0.1.dist-info/METADATA
Tensor_Library-0.0.1.dist-info/WHEEL
Tensor_Library-0.0.1.dist-info/top_level.txt
Tensor_Library-0.0.1.dist-info/RECORD
