Metadata-Version: 2.1
Name: Tensor-Library
Version: 0.0.1
Summary: It is a simple library for the Python programming language. It will be updated frequently.
Home-page: https://github.com/andrekornyk/Library-for-Python-by-DexTeam?tab=readme-ov-file
Author: DexTeam
Author-email: bankcommandoofficial@gmail.com
Project-URL: GitHub, https://github.com/andrekornyk/Library-for-Python-by-DexTeam?tab=readme-ov-file
Keywords: files speedfiles
Classifier: Programming Language :: Python :: 3.11
Classifier: License :: OSI Approved :: MIT License
Classifier: Operating System :: OS Independent
Requires-Python: >=3.8
Requires-Dist: requests >=2.25.1
